[
    {
        "dni": "00000000A",
        "password": "d033e22ae348aeb5660fc2140aec35850c4da997",
        "lastAccess": "2022-02-07 23:15:08.274731",
        "isAdmin": true,
        "paid": true
    },
    {
        "dni": "71373589N",
        "password": "adminM",
        "lastAccess": "00/00/00 - 00:00:00",
        "isAdmin": true,
        "paid": true
    },
    {
        "dni": "75456784H",
        "password": "fvalor",
        "lastAccess": "00/00/00 - 00:00:00",
        "isAdmin": false,
        "paid": true
    }
]